{
  "generatedAtIso": "2026-05-04T12:22:10.848Z",
  "cityLabel": "ANNECY",
  "diamonds": [
    {
      "name": "Le Fournil d’Annecy (mock D1)",
      "metier": "Boulangerie",
      "address": "14 rue Sommeiller, 74000 Annecy",
      "rating": 4.6,
      "reviews": 132,
      "lost_revenue_pitch": "Avec un volume d’avis qui prouve le flux, l’absence totale de site vous fait perdre une part importante des contacts qui veulent passer à l’action après Maps — au profit des concurrents déjà cliquables en un tap.",
      "maps_cover_image_url": "https://example.test/maps-cover-mock-annecy.jpg",
      "diamond_pain": "diamant_brut",
      "seed_category": "urgence plomberie Annecy",
      "place_id": "ChIJdiam000000000000000000001",
      "trending_query": "urgence plomberie Annecy",
      "strate_score_total": 100,
      "strate_is_diamant_brut": true,
      "strate_failures_vulgarized": [
        "Pas de site web : le trafic Maps ne trouve aucune passerelle de conversion en ligne."
      ]
    }
  ],
  "demand_driven_mode": true,
  "trending_queries_used": [
    "urgence plomberie Annecy",
    "dépannage chauffage Annecy",
    "réparation électroménager Annecy",
    "devis rénovation Annecy",
    "installation cuisine Annecy",
    "location matériel Annecy",
    "meilleur artisan Annecy",
    "spécialiste fuite Annecy",
    "réparation voiture Annecy",
    "dépannage serrure Annecy"
  ]
}
